silero_stress/__init__.py
silero_stress/accentor.py
silero_stress/simple_accentor.py
silero_stress/data/accentor-bel.pt
silero_stress/data/accentor-ukr.pt
silero_stress/data/accentor.pt
silero_stress/data/vocabularies/vocab-aze_cyr.gz
silero_stress/data/vocabularies/vocab-aze_lat.gz
silero_stress/data/vocabularies/vocab-bak.gz
silero_stress/data/vocabularies/vocab-bel.gz
silero_stress/data/vocabularies/vocab-chv.gz
silero_stress/data/vocabularies/vocab-erz.gz
silero_stress/data/vocabularies/vocab-hye.gz
silero_stress/data/vocabularies/vocab-kat.gz
silero_stress/data/vocabularies/vocab-kaz.gz
silero_stress/data/vocabularies/vocab-kbd.gz
silero_stress/data/vocabularies/vocab-kir.gz
silero_stress/data/vocabularies/vocab-kjh.gz
silero_stress/data/vocabularies/vocab-mdf.gz
silero_stress/data/vocabularies/vocab-sah.gz
silero_stress/data/vocabularies/vocab-tat.gz
silero_stress/data/vocabularies/vocab-tgk.gz
silero_stress/data/vocabularies/vocab-udm.gz
silero_stress/data/vocabularies/vocab-uzb_cyr.gz
silero_stress/data/vocabularies/vocab-uzb_lat.gz
silero_stress/data/vocabularies/vocab-xal.gz
silero_stress-1.3.dist-info/METADATA
silero_stress-1.3.dist-info/WHEEL
silero_stress-1.3.dist-info/licenses/LICENSE
silero_stress-1.3.dist-info/RECORD
